sanctumlabs_dbkit/__init__.py
sanctumlabs_dbkit/document/__init__.py
sanctumlabs_dbkit/exceptions.py
sanctumlabs_dbkit/nosql/__init__.py
sanctumlabs_dbkit/protocols.py
sanctumlabs_dbkit/sql/__init__.py
sanctumlabs_dbkit/sql/callbacks.py
sanctumlabs_dbkit/sql/logger.py
sanctumlabs_dbkit/sql/mixins.py
sanctumlabs_dbkit/sql/models.py
sanctumlabs_dbkit/sql/repository.py
sanctumlabs_dbkit/sql/session.py
sanctumlabs_dbkit/sql/types.py
sanctumlabs_dbkit/sql/utils.py
sanctumlabs_dbkit/utils.py
sanctumlabs_dbkit-1.0.0.dist-info/LICENSE
sanctumlabs_dbkit-1.0.0.dist-info/METADATA
sanctumlabs_dbkit-1.0.0.dist-info/WHEEL
sanctumlabs_dbkit-1.0.0.dist-info/RECORD
