Metadata-Version: 2.1
Name: sanctumlabs-dbkit
Version: 1.0.0
Summary: A wrapper for database libraries which bakes in common database functionality.
License: MIT
Author: BrianLusina
Author-email: 12752833+BrianLusina@users.noreply.github.com
Requires-Python: >=3.12.0,<4.0.0
Classifier: License :: OSI Approved :: MIT License
Classifier: Programming Language :: Python :: 3
Requires-Dist: inflection (>=0.5.1,<0.6.0)
Requires-Dist: sqlalchemy (>=2.0.29,<3.0.0)
Requires-Dist: sqlalchemy-utils (>=0.41.1,<0.42.0)
